{
  "60001": {
    "DungeonDes": "FeinaEvent_DungeonDes_1",
    "DungeonId": 60001,
    "DungeonName": "FeinaEvent_DungeonName_1",
    "DungeonSDes": "FeinaEvent_SimpleDungeonDes_1",
    "Level": [
      3,
      6,
      8
    ],
    "LevelDes": [
      "FeinaEvent_DungeonTask_1",
      "FeinaEvent_DungeonTask_2",
      "FeinaEvent_DungeonTask_3"
    ],
    "LockToast": "FeinaEvent_DungeonLock_1",
    "PassReward": 110104,
    "Reward": [
      110101,
      110102,
      110103
    ],
    "RewardPreview": 1030061,
    "SettlementId": 1030101
  },
  "60002": {
    "DungeonDes": "FeinaEvent_DungeonDes_2",
    "DungeonId": 60002,
    "DungeonName": "FeinaEvent_DungeonName_2",
    "DungeonSDes": "FeinaEvent_SimpleDungeonDes_2",
    "Level": [
      3,
      6,
      8
    ],
    "LevelDes": [
      "FeinaEvent_DungeonTask_1",
      "FeinaEvent_DungeonTask_2",
      "FeinaEvent_DungeonTask_3"
    ],
    "LockToast": "FeinaEvent_DungeonLock_2",
    "PassReward": 110104,
    "Reward": [
      110101,
      110102,
      110103
    ],
    "RewardPreview": 1030061,
    "SettlementId": 1030102
  },
  "60003": {
    "DungeonDes": "FeinaEvent_DungeonDes_3",
    "DungeonId": 60003,
    "DungeonName": "FeinaEvent_DungeonName_3_1",
    "DungeonSDes": "FeinaEvent_SimpleDungeonDes_3_1",
    "Level": [
      3,
      6,
      8
    ],
    "LevelDes": [
      "FeinaEvent_DungeonTask_1",
      "FeinaEvent_DungeonTask_2",
      "FeinaEvent_DungeonTask_3"
    ],
    "LockToast": "FeinaEvent_DungeonLock_3",
    "PassReward": 110104,
    "Reward": [
      110101,
      110102,
      110103
    ],
    "RewardPreview": 1030061,
    "SettlementId": 1030103
  },
  "60004": {
    "DungeonDes": "FeinaEvent_DungeonDes_3",
    "DungeonId": 60004,
    "DungeonName": "FeinaEvent_DungeonName_3_2",
    "DungeonSDes": "FeinaEvent_SimpleDungeonDes_3_2",
    "Level": [
      3,
      6,
      8
    ],
    "LevelDes": [
      "FeinaEvent_DungeonTask_1",
      "FeinaEvent_DungeonTask_2",
      "FeinaEvent_DungeonTask_3"
    ],
    "LockToast": "FeinaEvent_DungeonLock_3_2",
    "PassReward": 110104,
    "PreDungeon": 60003,
    "Reward": [
      110101,
      110102,
      110103
    ],
    "RewardPreview": 1030061,
    "SettlementId": 1030104
  },
  "60005": {
    "DungeonDes": "FeinaEvent_DungeonDes_4",
    "DungeonId": 60005,
    "DungeonName": "FeinaEvent_DungeonName_4_1",
    "DungeonSDes": "FeinaEvent_SimpleDungeonDes_4_1",
    "Level": [
      3,
      6,
      8
    ],
    "LevelDes": [
      "FeinaEvent_DungeonTask_1",
      "FeinaEvent_DungeonTask_2",
      "FeinaEvent_DungeonTask_3"
    ],
    "LockToast": "FeinaEvent_DungeonLock_4",
    "PassReward": 110104,
    "Reward": [
      110101,
      110102,
      110103
    ],
    "RewardPreview": 1030061,
    "SettlementId": 1030105
  },
  "60006": {
    "DungeonDes": "FeinaEvent_DungeonDes_4",
    "DungeonId": 60006,
    "DungeonName": "FeinaEvent_DungeonName_4_2",
    "DungeonSDes": "FeinaEvent_SimpleDungeonDes_4_2",
    "Level": [
      3,
      6,
      8
    ],
    "LevelDes": [
      "FeinaEvent_DungeonTask_1",
      "FeinaEvent_DungeonTask_2",
      "FeinaEvent_DungeonTask_3"
    ],
    "LockToast": "FeinaEvent_DungeonLock_4_2",
    "PassReward": 110104,
    "PreDungeon": 60005,
    "Reward": [
      110101,
      110102,
      110103
    ],
    "RewardPreview": 1030061,
    "SettlementId": 1030106
  }
}